[
  {"type": "landing-modern", "title": "Modern Landing", "subtitle": "Şık ve modern landing page.", "category": "Landing", "color": "purple", "icon": "rectangle.stack.fill"},
  {"type": "landing-startup", "title": "Startup", "subtitle": "Girişim tanıtım sayfası.", "category": "Landing", "color": "cyan", "icon": "rocket.fill"},
  {"type": "landing-agency", "title": "Ajans Sitesi", "subtitle": "Dijital ajans sayfası.", "category": "Landing", "color": "pink", "icon": "sparkles"},
  {"type": "landing-app", "title": "App Landing", "subtitle": "Mobil uygulama tanıtımı.", "category": "Landing", "color": "indigo", "icon": "iphone"},
  {"type": "landing-saas", "title": "SaaS Landing", "subtitle": "Yazılım ürün tanıtımı.", "category": "Landing", "color": "blue", "icon": "cloud.fill"},
  {"type": "landing-restaurant", "title": "Restaurant", "subtitle": "Restoran tanıtım sitesi.", "category": "Landing", "color": "orange", "icon": "fork.knife"},
  {"type": "landing-coffee", "title": "Coffee Shop", "subtitle": "Kafe ve kahve dükkanı.", "category": "Landing", "color": "brown", "icon": "cup.and.saucer.fill"},
  {"type": "landing-travel", "title": "Travel", "subtitle": "Gezi ve tur sayfası.", "category": "Landing", "color": "teal", "icon": "airplane"},
  {"type": "landing-fashion", "title": "Fashion Brand", "subtitle": "Moda marka sayfası.", "category": "Landing", "color": "pink", "icon": "tshirt.fill"},
  {"type": "landing-fitness", "title": "Fitness", "subtitle": "Spor ve fitness sayfası.", "category": "Landing", "color": "green", "icon": "figure.run"},
  {"type": "landing-music", "title": "Music Band", "subtitle": "Müzik grubu tanıtımı.", "category": "Landing", "color": "purple", "icon": "music.note"},
  {"type": "landing-event", "title": "Event Page", "subtitle": "Etkinlik tanıtım sayfası.", "category": "Landing", "color": "yellow", "icon": "calendar"},
  {"type": "landing-charity", "title": "Charity", "subtitle": "Bağış ve yardım kuruluşu.", "category": "Landing", "color": "red", "icon": "heart.fill"},
  {"type": "landing-realestate", "title": "Real Estate", "subtitle": "Emlak tanıtım sayfası.", "category": "Landing", "color": "orange", "icon": "house.fill"},
  {"type": "landing-wedding", "title": "Wedding", "subtitle": "Düğün davet sayfası.", "category": "Landing", "color": "pink", "icon": "heart.circle.fill"},
  {"type": "landing-crypto", "title": "Crypto", "subtitle": "Kripto para tanıtımı.", "category": "Landing", "color": "yellow", "icon": "bitcoinsign.circle.fill"},
  {"type": "landing-nft", "title": "NFT Collection", "subtitle": "NFT koleksiyon sayfası.", "category": "Landing", "color": "purple", "icon": "photo.artframe"},
  {"type": "landing-podcast", "title": "Podcast", "subtitle": "Podcast tanıtım sayfası.", "category": "Landing", "color": "indigo", "icon": "mic.fill"},
  {"type": "landing-course", "title": "Online Course", "subtitle": "Online eğitim platformu.", "category": "Landing", "color": "blue", "icon": "book.fill"},
  {"type": "landing-clinic", "title": "Clinic", "subtitle": "Sağlık klinik sayfası.", "category": "Landing", "color": "cyan", "icon": "cross.fill"},

  {"type": "portfolio-developer", "title": "Developer CV", "subtitle": "Yazılımcı portföyü.", "category": "Portfolio", "color": "blue", "icon": "chevron.left.forwardslash.chevron.right"},
  {"type": "portfolio-designer", "title": "Designer", "subtitle": "Tasarımcı portföyü.", "category": "Portfolio", "color": "pink", "icon": "paintbrush.fill"},
  {"type": "portfolio-photographer", "title": "Photography", "subtitle": "Fotoğrafçı portföyü.", "category": "Portfolio", "color": "yellow", "icon": "camera.fill"},
  {"type": "portfolio-personal", "title": "Personal Blog", "subtitle": "Kişisel blog sayfası.", "category": "Portfolio", "color": "purple", "icon": "person.fill"},
  {"type": "portfolio-resume", "title": "Resume", "subtitle": "Online özgeçmiş.", "category": "Portfolio", "color": "green", "icon": "doc.text.fill"},
  {"type": "portfolio-architect", "title": "Architect", "subtitle": "Mimar portföy sayfası.", "category": "Portfolio", "color": "orange", "icon": "building.2.fill"},
  {"type": "portfolio-illustrator", "title": "Illustrator", "subtitle": "İllüstratör portföyü.", "category": "Portfolio", "color": "pink", "icon": "pencil.tip"},
  {"type": "portfolio-writer", "title": "Writer", "subtitle": "Yazar tanıtım sayfası.", "category": "Portfolio", "color": "indigo", "icon": "text.book.closed.fill"},
  {"type": "portfolio-videographer", "title": "Videographer", "subtitle": "Video yapımcı portföyü.", "category": "Portfolio", "color": "red", "icon": "video.fill"},
  {"type": "portfolio-musician", "title": "Musician", "subtitle": "Müzisyen tanıtım sayfası.", "category": "Portfolio", "color": "purple", "icon": "music.quarternote.3"},
  {"type": "portfolio-freelancer", "title": "Freelancer", "subtitle": "Freelancer tanıtım sayfası.", "category": "Portfolio", "color": "cyan", "icon": "laptopcomputer"},
  {"type": "portfolio-agency-team", "title": "Agency Team", "subtitle": "Ajans ekip sayfası.", "category": "Portfolio", "color": "blue", "icon": "person.3.fill"},
  {"type": "portfolio-3d-artist", "title": "3D Artist", "subtitle": "3D sanatçı portföyü.", "category": "Portfolio", "color": "orange", "icon": "cube.fill"},
  {"type": "portfolio-ux", "title": "UX Designer", "subtitle": "UX tasarımcı portföyü.", "category": "Portfolio", "color": "teal", "icon": "hand.draw.fill"},
  {"type": "portfolio-brand", "title": "Brand Identity", "subtitle": "Marka kimlik portföyü.", "category": "Portfolio", "color": "yellow", "icon": "star.fill"},

  {"type": "shop-modern", "title": "Modern Shop", "subtitle": "Modern e-ticaret sitesi.", "category": "E-Ticaret", "color": "green", "icon": "cart.fill"},
  {"type": "shop-fashion", "title": "Fashion Store", "subtitle": "Moda mağazası.", "category": "E-Ticaret", "color": "pink", "icon": "tshirt.fill"},
  {"type": "shop-electronics", "title": "Electronics", "subtitle": "Elektronik mağazası.", "category": "E-Ticaret", "color": "blue", "icon": "cpu.fill"},
  {"type": "shop-food", "title": "Food Delivery", "subtitle": "Yemek sipariş sitesi.", "category": "E-Ticaret", "color": "orange", "icon": "fork.knife.circle.fill"},
  {"type": "shop-jewelry", "title": "Jewelry", "subtitle": "Mücevher mağazası.", "category": "E-Ticaret", "color": "yellow", "icon": "diamond.fill"},
  {"type": "shop-books", "title": "Bookstore", "subtitle": "Kitap mağazası.", "category": "E-Ticaret", "color": "indigo", "icon": "books.vertical.fill"},
  {"type": "shop-sport", "title": "Sport Shop", "subtitle": "Spor malzemeleri.", "category": "E-Ticaret", "color": "green", "icon": "sportscourt.fill"},
  {"type": "shop-beauty", "title": "Beauty Store", "subtitle": "Kozmetik mağazası.", "category": "E-Ticaret", "color": "pink", "icon": "sparkles"},
  {"type": "shop-furniture", "title": "Furniture", "subtitle": "Mobilya mağazası.", "category": "E-Ticaret", "color": "brown", "icon": "sofa.fill"},
  {"type": "shop-product", "title": "Product Page", "subtitle": "Ürün detay sayfası.", "category": "E-Ticaret", "color": "purple", "icon": "shippingbox.fill"},
  {"type": "shop-pricing", "title": "Pricing Table", "subtitle": "Fiyatlandırma tablosu.", "category": "E-Ticaret", "color": "cyan", "icon": "creditcard.fill"},
  {"type": "shop-checkout", "title": "Checkout", "subtitle": "Ödeme sayfası.", "category": "E-Ticaret", "color": "green", "icon": "bag.fill"},
  {"type": "shop-market", "title": "Market", "subtitle": "Market ürün listesi.", "category": "E-Ticaret", "color": "teal", "icon": "cart.badge.plus"},
  {"type": "shop-subscription", "title": "Subscription", "subtitle": "Abonelik planları.", "category": "E-Ticaret", "color": "purple", "icon": "arrow.clockwise.circle.fill"},
  {"type": "shop-digital", "title": "Digital Products", "subtitle": "Dijital ürün mağazası.", "category": "E-Ticaret", "color": "blue", "icon": "square.and.arrow.down.fill"},

  {"type": "auth-login", "title": "Login", "subtitle": "Giriş formu.", "category": "Auth", "color": "pink", "icon": "lock.fill"},
  {"type": "auth-register", "title": "Register", "subtitle": "Kayıt formu.", "category": "Auth", "color": "blue", "icon": "person.badge.plus"},
  {"type": "auth-forgot", "title": "Forgot Password", "subtitle": "Şifre sıfırlama.", "category": "Auth", "color": "orange", "icon": "key.fill"},
  {"type": "auth-profile", "title": "Profile", "subtitle": "Kullanıcı profili.", "category": "Auth", "color": "purple", "icon": "person.crop.circle.fill"},
  {"type": "auth-2fa", "title": "2FA Verify", "subtitle": "İki faktörlü doğrulama.", "category": "Auth", "color": "green", "icon": "shield.fill"},
  {"type": "auth-onboarding", "title": "Onboarding", "subtitle": "Kullanıcı karşılama.", "category": "Auth", "color": "cyan", "icon": "hand.wave.fill"},
  {"type": "auth-settings", "title": "Account Settings", "subtitle": "Hesap ayarları.", "category": "Auth", "color": "indigo", "icon": "gearshape.fill"},
  {"type": "auth-subscription", "title": "Subscription", "subtitle": "Plan seçim ekranı.", "category": "Auth", "color": "yellow", "icon": "crown.fill"},
  {"type": "auth-delete", "title": "Delete Account", "subtitle": "Hesap silme ekranı.", "category": "Auth", "color": "red", "icon": "trash.fill"},
  {"type": "auth-success", "title": "Success Page", "subtitle": "İşlem başarılı ekranı.", "category": "Auth", "color": "green", "icon": "checkmark.circle.fill"},

  {"type": "dash-admin", "title": "Admin Panel", "subtitle": "Yönetim paneli.", "category": "Dashboard", "color": "indigo", "icon": "square.grid.2x2.fill"},
  {"type": "dash-analytics", "title": "Analytics", "subtitle": "İstatistik paneli.", "category": "Dashboard", "color": "cyan", "icon": "chart.bar.fill"},
  {"type": "dash-finance", "title": "Finance", "subtitle": "Finans takip paneli.", "category": "Dashboard", "color": "green", "icon": "banknote.fill"},
  {"type": "dash-crm", "title": "CRM", "subtitle": "Müşteri yönetim paneli.", "category": "Dashboard", "color": "blue", "icon": "person.2.fill"},
  {"type": "dash-ecommerce", "title": "E-Commerce Panel", "subtitle": "Satış yönetim paneli.", "category": "Dashboard", "color": "orange", "icon": "chart.line.uptrend.xyaxis"},
  {"type": "dash-tasks", "title": "Task Manager", "subtitle": "Görev yönetim paneli.", "category": "Dashboard", "color": "yellow", "icon": "checklist"},
  {"type": "dash-social", "title": "Social Media", "subtitle": "Sosyal medya paneli.", "category": "Dashboard", "color": "pink", "icon": "heart.fill"},
  {"type": "dash-health", "title": "Health Tracker", "subtitle": "Sağlık takip paneli.", "category": "Dashboard", "color": "red", "icon": "heart.text.square.fill"},
  {"type": "dash-crypto", "title": "Crypto Dashboard", "subtitle": "Kripto takip paneli.", "category": "Dashboard", "color": "yellow", "icon": "chart.pie.fill"},
  {"type": "dash-project", "title": "Project Manager", "subtitle": "Proje yönetim paneli.", "category": "Dashboard", "color": "purple", "icon": "folder.fill"},

  {"type": "app-calculator", "title": "Calculator", "subtitle": "Hesap makinesi.", "category": "Mini App", "color": "orange", "icon": "plus.forwardslash.minus"},
  {"type": "app-weather", "title": "Weather", "subtitle": "Hava durumu.", "category": "Mini App", "color": "cyan", "icon": "cloud.sun.fill"},
  {"type": "app-todo", "title": "To Do", "subtitle": "Yapılacaklar listesi.", "category": "Mini App", "color": "green", "icon": "checklist"},
  {"type": "app-music", "title": "Music Player", "subtitle": "Müzik çalar.", "category": "Mini App", "color": "pink", "icon": "music.note"},
  {"type": "app-movie", "title": "Movie Card", "subtitle": "Film kartı.", "category": "Mini App", "color": "purple", "icon": "film.fill"},
  {"type": "app-clock", "title": "Clock", "subtitle": "Saat ve alarm.", "category": "Mini App", "color": "blue", "icon": "clock.fill"},
  {"type": "app-notes", "title": "Notes", "subtitle": "Not alma uygulaması.", "category": "Mini App", "color": "yellow", "icon": "note.text"},
  {"type": "app-quiz", "title": "Quiz App", "subtitle": "Soru cevap oyunu.", "category": "Mini App", "color": "indigo", "icon": "questionmark.circle.fill"},
  {"type": "app-countdown", "title": "Countdown", "subtitle": "Geri sayım sayacı.", "category": "Mini App", "color": "red", "icon": "timer"},
  {"type": "app-currency", "title": "Currency", "subtitle": "Döviz çevirici.", "category": "Mini App", "color": "green", "icon": "dollarsign.circle.fill"},
  {"type": "app-bmi", "title": "BMI Calculator", "subtitle": "Vücut kitle hesaplayıcı.", "category": "Mini App", "color": "teal", "icon": "figure.stand"},
  {"type": "app-pomodoro", "title": "Pomodoro", "subtitle": "Pomodoro zamanlayıcı.", "category": "Mini App", "color": "red", "icon": "timer.circle.fill"},
  {"type": "app-color", "title": "Color Picker", "subtitle": "Renk seçici araç.", "category": "Mini App", "color": "pink", "icon": "paintpalette.fill"},
  {"type": "app-dice", "title": "Dice Roller", "subtitle": "Zar atma uygulaması.", "category": "Mini App", "color": "purple", "icon": "die.face.5.fill"},
  {"type": "app-qr", "title": "QR Generator", "subtitle": "QR kod oluşturucu.", "category": "Mini App", "color": "orange", "icon": "qrcode"},

  {"type": "blog-minimal", "title": "Minimal Blog", "subtitle": "Sade blog tasarımı.", "category": "Blog", "color": "indigo", "icon": "text.alignleft"},
  {"type": "blog-magazine", "title": "Magazine", "subtitle": "Dergi tarzı blog.", "category": "Blog", "color": "red", "icon": "newspaper.fill"},
  {"type": "blog-tech", "title": "Tech Blog", "subtitle": "Teknoloji blog sayfası.", "category": "Blog", "color": "blue", "icon": "cpu.fill"},
  {"type": "blog-travel", "title": "Travel Blog", "subtitle": "Seyahat blog sayfası.", "category": "Blog", "color": "teal", "icon": "map.fill"},
  {"type": "blog-food", "title": "Food Blog", "subtitle": "Yemek blog sayfası.", "category": "Blog", "color": "orange", "icon": "fork.knife"},
  {"type": "blog-lifestyle", "title": "Lifestyle", "subtitle": "Yaşam tarzı blogu.", "category": "Blog", "color": "pink", "icon": "heart.fill"},
  {"type": "blog-news", "title": "News Site", "subtitle": "Haber sitesi tasarımı.", "category": "Blog", "color": "cyan", "icon": "megaphone.fill"},
  {"type": "blog-dark", "title": "Dark Blog", "subtitle": "Koyu tema blog.", "category": "Blog", "color": "purple", "icon": "moon.fill"},
  {"type": "blog-photo", "title": "Photo Blog", "subtitle": "Fotoğraf blog sayfası.", "category": "Blog", "color": "yellow", "icon": "photo.fill"},
  {"type": "blog-podcast", "title": "Podcast Blog", "subtitle": "Podcast blog sayfası.", "category": "Blog", "color": "green", "icon": "mic.fill"},

  {"type": "game-memory", "title": "Memory Game", "subtitle": "Hafıza kart oyunu.", "category": "Oyun", "color": "purple", "icon": "rectangle.grid.3x2.fill"},
  {"type": "game-snake", "title": "Snake", "subtitle": "Yılan oyunu.", "category": "Oyun", "color": "green", "icon": "gamecontroller.fill"},
  {"type": "game-tictactoe", "title": "Tic Tac Toe", "subtitle": "XOX oyunu.", "category": "Oyun", "color": "blue", "icon": "grid"},
  {"type": "game-breakout", "title": "Breakout", "subtitle": "Top ve tuğla oyunu.", "category": "Oyun", "color": "orange", "icon": "square.grid.4x3.fill"},
  {"type": "game-typing", "title": "Typing Game", "subtitle": "Yazma hızı oyunu.", "category": "Oyun", "color": "cyan", "icon": "keyboard.fill"}
  {"type": "code-csharp-hello", "title": "C# Merhaba Dunya", "subtitle": "Basit C# konsol uygulamasi ornegi.", "category": "Code", "color": "purple", "icon": "chevron.left.forwardslash.chevron.right"}
]
